{
  "bundleId": "fictional-theft-ashleigh-merritt",
  "fictional": true,
  "label": "R v Ashleigh Merritt — theft",
  "purpose": "Theft bundle with Listed hearing date",
  "sourceType": "single-text-file",
  "sourceRef": "docs/fictional-bundle-theft/FICTIONAL_THEFT_BUNDLE_COPY_PASTE.txt",
  "linkStatus": "runnable",
  "defendant": "Ashleigh Merritt",
  "aliases": ["Merritt"],
  "charge": "Theft, contrary to s.1 Theft Act 1968",
  "chargeKeywords": ["theft", "theft act"],
  "court": null,
  "hearingDate": "2024-05-14",
  "stage": null,
  "documentTypesExpected": ["charge_sheet", "mg5"],
  "documentTypesForbidden": [],
  "evidenceSignalsExpected": [],
  "missingMaterialExpected": [],
  "thinBundleExpected": false,
  "expectedWorkflowProfile": "generic",
  "expectedRouteFamily": null,
  "prohibitedFamilies": ["fraud_account_control", "pwits_phone_attribution"],
  "expectedProvisionalStatus": false,
  "humanReviewExpected": false,
  "notes": "Theft shape — must not map to fraud/PWITS/robbery."
}
